{
  "trainingPhrases": [ {
    "parts": [ {
      "text": "ok",
      "parameterId": "confirmation",
      "auto": true
    } ],
    "repeatCount": 1,
    "languageCode": "en"
  }, {
    "parts": [ {
      "text": "oka",
      "parameterId": "confirmation",
      "auto": true
    } ],
    "repeatCount": 1,
    "languageCode": "en"
  }, {
    "parts": [ {
      "text": "okay",
      "parameterId": "confirmation",
      "auto": true
    } ],
    "repeatCount": 1,
    "languageCode": "en"
  }, {
    "parts": [ {
      "text": "yeah",
      "parameterId": "confirmation",
      "auto": true
    } ],
    "repeatCount": 1,
    "languageCode": "en"
  }, {
    "parts": [ {
      "text": "nop",
      "parameterId": "confirmation"
    } ],
    "repeatCount": 1,
    "languageCode": "en"
  }, {
    "parts": [ {
      "text": "no",
      "parameterId": "confirmation",
      "auto": true
    } ],
    "repeatCount": 1,
    "languageCode": "en"
  }, {
    "parts": [ {
      "text": "yes",
      "parameterId": "confirmation",
      "auto": true
    } ],
    "repeatCount": 1,
    "languageCode": "en"
  } ]
}
